urff/__init__.py
urff-1.0.dist-info/METADATA
urff-1.0.dist-info/WHEEL
urff-1.0.dist-info/top_level.txt
urff-1.0.dist-info/RECORD
