Metadata-Version: 2.1
Name: urff
Version: 1.0
Summary: A typo package to prevent typos.
Author-email: Sinan Islekdemir <sinan@islekdemir.com>
Classifier: Programming Language :: Python :: 3
Classifier: License :: OSI Approved :: MIT License
Classifier: Operating System :: OS Independent
Requires-Python: >=3.6
